{"status":"ok","message-type":"work","message-version":"1.0.0","message":{"indexed":{"date-parts":[[2018,4,30]],"date-time":"2018-04-30T15:55:25Z","timestamp":1525103725384},"publisher-location":"New York, New York, USA","reference-count":33,"publisher":"ACM Press","license":[{"URL":"http:\/\/www.acm.org\/publications\/policies\/copyright_policy#Background","start":{"date-parts":[[2018,4,23]],"date-time":"2018-04-23T00:00:00Z","timestamp":1524441600000},"delay-in-days":112,"content-version":"vor"}],"content-domain":{"domain":[],"crossmark-restriction":false},"short-container-title":[],"published-print":{"date-parts":[[2018]]},"DOI":"10.1145\/3184558.3191601","type":"proceedings-article","created":{"date-parts":[[2018,4,18]],"date-time":"2018-04-18T18:04:25Z","timestamp":1524074665000},"source":"Crossref","is-referenced-by-count":0,"title":["Generating Schema Labels through Dataset Content Analysis"],"prefix":"10.1145","author":[{"given":"Zhiyu","family":"Chen","sequence":"first","affiliation":[{"name":"Lehigh University, Bethlehem, PA, USA"}]},{"given":"Haiyan","family":"Jia","sequence":"additional","affiliation":[{"name":"Lehigh University, Bethlehem, PA, USA"}]},{"given":"Jeff","family":"Heflin","sequence":"additional","affiliation":[{"name":"Lehigh University, Bethlehem, PA, USA"}]},{"given":"Brian D.","family":"Davison","sequence":"additional","affiliation":[{"name":"Lehigh University, Bethlehem, PA, USA"}]}],"member":"320","reference":[{"key":"key-10.1145\/3184558.3191601-1","unstructured":"Mohamed Ben Ellefi, Zohra Bellahsene, Stefan Dietze, and Konstantin Todorov. 2016. Dataset Recommendation for Data Linking: An Intensional Approach. In The Semantic Web. Latest Advances and New Domains. Springer, 36--51.","DOI":"10.1007\/978-3-319-34129-3_3","doi-asserted-by":"crossref"},{"key":"key-10.1145\/3184558.3191601-2","unstructured":"Jacob Berlin and Amihai Motro. 2002. Database Schema Matching Using Machine Learning with Feature Selection. In Advanced Information Systems Engineering. Springer, 452--466.","DOI":"10.1007\/3-540-47961-9_32","doi-asserted-by":"crossref"},{"key":"key-10.1145\/3184558.3191601-3","unstructured":"Chandra Sekhar Bhagavatula, Thanapon Noraset, and Doug Downey. 2015. TabEL: Entity Linking in Web Tables. In The Semantic Web - ISWC 2015. Springer, 425-- 441.","DOI":"10.1007\/978-3-319-25007-6_25","doi-asserted-by":"crossref"},{"key":"key-10.1145\/3184558.3191601-4","unstructured":"Silvana Castano and Valeria De Antonellis. 2001. Global viewing of heterogeneous data sources. IEEE Trans. on Knowledge and Data Eng. 13, 2 (2001), 277--297.","DOI":"10.1109\/69.917566","doi-asserted-by":"crossref"},{"key":"key-10.1145\/3184558.3191601-5","unstructured":"H&#233;lio Rodrigues de Oliveira, Alberto Trindade Tavares, and Bernadette Farias L&#243;scio. 2012. Feedback-based Data Set Recommendation for Building Linked Data Applications. In Proc. 8th Intl Conf. on Semantic Systems (I-SEMANTICS '12). ACM, 49--55."},{"key":"key-10.1145\/3184558.3191601-6","unstructured":"Hong-Hai Do and Erhard Rahm. 2002. COMA-a system for flexible combination of schema matching approaches. In Proc. 28th Intl Conf. on Very Large Databases. Elsevier, 610--621.","DOI":"10.1016\/B978-155860869-6\/50060-3","doi-asserted-by":"crossref"},{"key":"key-10.1145\/3184558.3191601-7","unstructured":"Julian Eberius, Katrin Braunschweig, Markus Hentsch, Maik Thiele, Ahmad Ahmadov, and Wolfgang Lehner. 2015. Building the resden web table corpus: A classification approach. In IEEE\/ACM 2nd Intl Symp. on Big Data Computing (BDC). 41--50."},{"key":"key-10.1145\/3184558.3191601-8","unstructured":"Mohamed Ben Ellefi, Zohra Bellahsene, Stefan Dietze, and Konstantin Todorov. 2016. Beyond established knowledge graphs-recommending web datasets for data linking. In Intl Conf. on Web Engineering. Springer, 262--279.","DOI":"10.1007\/978-3-319-38791-8_15","doi-asserted-by":"crossref"},{"key":"key-10.1145\/3184558.3191601-9","unstructured":"Jing Fang, Prasenjit Mitra, Zhi Tang, and C. Lee Giles. 2012. Table Header Detection and Classification. In Proc. 26th AAAI Conf. on Artificial Intelligence (AAAI'12). AAAI Press, 599--605."},{"key":"key-10.1145\/3184558.3191601-10","unstructured":"Matthew Hurst. 2001. Layout and Language: Challenges for Table Understanding on the Web. In Proc. Intl Workshop on Web Document Analysis. 27--30."},{"key":"key-10.1145\/3184558.3191601-11","unstructured":"Luiz Andr&#233; P Paes Leme, Giseli Rabello Lopes, Bernardo Pereira Nunes, Marco Antonio Casanova, and Stefan Dietze. 2013. Identifying candidate datasets for data interlinking. In Intl Conf. on Web Engineering. Springer, 354--366."},{"key":"key-10.1145\/3184558.3191601-12","unstructured":"Jimmy Lin and Boris Katz. 2003. Question Answering from the Web Using Knowledge Annotation and Knowledge Mining Techniques. In Proc. 12th Intl Conf. on Information and Knowledge Management (CIKM '03). ACM, 116--123. https:\/\/doi.org\/10.1145\/956863.956886","DOI":"10.1145\/956863.956886","doi-asserted-by":"crossref"},{"key":"key-10.1145\/3184558.3191601-13","unstructured":"Giseli Rabello Lopes, Luiz Andr&#233; P Paes Leme, Bernardo Pereira Nunes, and Marco A Casanova. 2014. RecLAK: Analysis and Recommendation of Interlinking Datasets. In LAK Workshops."},{"key":"key-10.1145\/3184558.3191601-14","unstructured":"Jayant Madhavan, Philip A. Bernstein, and Erhard Rahm. 2001. Generic Schema Matching with Cupid. In Proc. 27th Intl Conf. on Very Large Data Bases (VLDB '01). Morgan Kaufmann, 49--58."},{"key":"key-10.1145\/3184558.3191601-15","unstructured":"Varish Mulwad, Tim Finin, and Anupam Joshi. 2013. Semantic Message Passing for Generating Linked Data from Tables. In The Semantic Web--ISWC 2013. Springer, 363--378.","DOI":"10.1007\/978-3-642-41335-3_23","doi-asserted-by":"crossref"},{"key":"key-10.1145\/3184558.3191601-16","unstructured":"Varish Mulwad, Tim Finin, Zareen Syed, and Anupam Joshi. 2010. T2LD: Interpreting and Representing Tables as Linked Data. In 9th Intl Semantic Web Conf. (ISWC). 25."},{"key":"key-10.1145\/3184558.3191601-17","unstructured":"Andriy Nikolov and Mathieu dAquin. 2011. Identifying relevant sources for data linking using a semantic web index. In WWW2011 Workshop: Linked Data on the Web (LDOW 2011)."},{"key":"key-10.1145\/3184558.3191601-18","unstructured":"Andriy Nikolov, Mathieu dAquin, and Enrico Motta. 2012. What Should I Link to Identifying Relevant Sources and Classes for Data Linking. In The Semantic Web. Springer, 284--299."},{"key":"key-10.1145\/3184558.3191601-19","unstructured":"Rakesh Pimplikar and Sunita Sarawagi. 2012. Answering Table Queries on the Web Using Column Keywords. Proc. VLDB Endow. 5, 10 (June 2012), 908--919.","DOI":"10.14778\/2336664.2336665","doi-asserted-by":"crossref"},{"key":"key-10.1145\/3184558.3191601-20","unstructured":"Erhard Rahm and Philip A. Bernstein. 2001. A survey of approaches to automatic schema matching. The VLDB Journal 10, 4 (01 Dec 2001), 334--350.","DOI":"10.1007\/s007780100057","doi-asserted-by":"crossref"},{"key":"key-10.1145\/3184558.3191601-21","unstructured":"L Ratinov and Ehud Gudes. 2004. Abbreviation expansion in schema matching and web integration. In Proc. IEEE\/WIC\/ACM Intl Conf. on Web Intelligence. 485--489.","DOI":"10.1109\/WI.2004.10083","doi-asserted-by":"crossref"},{"key":"key-10.1145\/3184558.3191601-22","unstructured":"Dominique Ritze, Oliver Lehmberg, Yaser Oulabi, and Christian Bizer. 2016. Profiling the Potential of Web Tables for Augmenting Cross-domain Knowledge Bases. In Proc. 25th Intl Conf. on World Wide Web (WWW '16). 251--261. https: \/\/doi.org\/10.1145\/2872427.2883017"},{"key":"key-10.1145\/3184558.3191601-23","unstructured":"Yoones A Sekhavat, Francesco Di Paolo, Denilson Barbosa, and Paolo Merialdo. 2014. Knowledge Base Augmentation using Tabular Data. In LDOW."},{"key":"key-10.1145\/3184558.3191601-24","unstructured":"Serena Sorrentino, Sonia Bergamaschi, and Maciej Gawinecki. 2011. NORMS: an automatic tool to perform schema label normalization. In Data Engineering (ICDE), 2011 IEEE 27th International Conference on. IEEE, 1344--1347.","DOI":"10.1109\/ICDE.2011.5767952","doi-asserted-by":"crossref"},{"key":"key-10.1145\/3184558.3191601-25","unstructured":"Serena Sorrentino, Sonia Bergamaschi, Maciej Gawinecki, and Laura Po. 2009. Schema Normalization for Improving Schema Matching. In Conceptual Modeling - ER 2009. Springer, 280--293.","DOI":"10.1007\/978-3-642-04840-1_22","doi-asserted-by":"crossref"},{"key":"key-10.1145\/3184558.3191601-26","unstructured":"Zareen Syed, Tim Finin, Varish Mulwad, and Anupam Joshi. 2010. Exploiting a web of semantic data for interpreting tables. In Proc. 2nd Web Science Conf., Vol. 5."},{"key":"key-10.1145\/3184558.3191601-27","unstructured":"Barbara Ubaldi. 2013. Open government data: Towards empirical analysis of open government data initiatives. OECD Working Papers on Public Governance 22 (2013), 0_1.","DOI":"10.1787\/5k46bj4f03s7-en","doi-asserted-by":"crossref"},{"key":"key-10.1145\/3184558.3191601-28","unstructured":"Isabel Valera and Zoubin Ghahramani. 2017. Automatic Discovery of the Statistical Types of Variables in a Dataset. In Proc. 34th Intl Conf. on Machine Learning (Proceedings of Machine Learning Research), Vol. 70. PMLR, 3521--3529."},{"key":"key-10.1145\/3184558.3191601-29","unstructured":"Petros Venetis, Alon Halevy, Jayant Madhavan, Marius Paca, Warren Shen, Fei Wu, Gengxin Miao, and Chung Wu. 2011. Recovering Semantics of Tables on the Web. Proc. VLDB Endow. 4, 9 (June 2011), 528--538.","DOI":"10.14778\/2002938.2002939","doi-asserted-by":"crossref"},{"key":"key-10.1145\/3184558.3191601-30","unstructured":"Jingjing Wang, Haixun Wang, Zhongyuan Wang, and Kenny Q. Zhu. 2012. Understanding Tables on the Web. In Conceptual Modeling. Springer, 141--155.","DOI":"10.1007\/978-3-642-34002-4_11","doi-asserted-by":"crossref"},{"key":"key-10.1145\/3184558.3191601-31","unstructured":"Yalin Wang and Jianying Hu. 2002. A Machine Learning Based Approach for Table Detection on the Web. In Proc. 11th Intl Conf. on World Wide Web (WWW '02). ACM, 242--250.","DOI":"10.1145\/511446.511478","doi-asserted-by":"crossref"},{"key":"key-10.1145\/3184558.3191601-32","unstructured":"Xiaolu Zhang, Yueguo Chen, Jinchuan Chen, Xiaoyong Du, and Lei Zou. 2013. Mapping Entity-Attribute Web Tables to Web-Scale Knowledge Bases. In Database Systems for Advanced Applications. Springer, 108--122.","DOI":"10.1007\/978-3-642-37450-0_8","doi-asserted-by":"crossref"},{"key":"key-10.1145\/3184558.3191601-33","unstructured":"Ziqi Zhang. 2014. Towards efficient and effective semantic table interpretation. In International Semantic Web Conference. Springer, 487--502.","DOI":"10.1007\/978-3-319-11964-9_31","doi-asserted-by":"crossref"}],"event":{"name":"Companion of the The Web Conference 2018","location":"Lyon, France","sponsor":["IW3C2, International World Wide Web Conference Committee","SIGWEB, ACM Special Interest Group on Hypertext, Hypermedia, and Web"],"acronym":"WWW '18","number":"2018","start":{"date-parts":[[2018,4,23]]},"end":{"date-parts":[[2018,4,27]]}},"container-title":["Companion of the The Web Conference 2018 on The Web Conference 2018  - WWW '18"],"original-title":[],"link":[{"URL":"http:\/\/dl.acm.org\/ft_gateway.cfm?id=3191601&ftid=1958441&dwn=1","content-type":"unspecified","content-version":"vor","intended-application":"similarity-checking"}],"deposited":{"date-parts":[[2018,4,18]],"date-time":"2018-04-18T20:49:40Z","timestamp":1524084580000},"score":1.0,"subtitle":[],"short-title":[],"issued":{"date-parts":[[2018]]},"ISBN":["9781450356404"],"references-count":33,"URL":"http:\/\/dx.doi.org\/10.1145\/3184558.3191601","relation":{"cites":[]}}}